st_comp_3dmodel/README.md
st_comp_3dmodel/__init__.py
st_comp_3dmodel/const.cp37-win_amd64.pyd
st_comp_3dmodel/init.cp37-win_amd64.pyd
st_comp_3dmodel/frontend_dist/favicon.ico
st_comp_3dmodel/frontend_dist/index.html
st_comp_3dmodel/frontend_dist/css/app.85f8003c.css
st_comp_3dmodel/frontend_dist/js/app.958c75c9.js
st_comp_3dmodel/frontend_dist/js/chunk-vendors.f3e53354.js
st_comp_3dmodel/frontend_dist/model/default.glb
st_comp_3dmodel-0.0.3.dist-info/METADATA
st_comp_3dmodel-0.0.3.dist-info/WHEEL
st_comp_3dmodel-0.0.3.dist-info/top_level.txt
st_comp_3dmodel-0.0.3.dist-info/RECORD
