Metadata-Version: 2.1
Name: st-comp-3dmodel
Version: 0.0.3
Summary: streamlit component for 3d model
Home-page: UNKNOWN
Author: spectereye
Author-email: spectereye@gmail.com
License: UNKNOWN
Platform: UNKNOWN
Requires-Python: >=3.7
Requires-Dist: streamlit (~=1.9.0)
Requires-Dist: protobuf (~=3.19.0)
